[
  {
    "inputs": [],
    "stateMutability": "nonpayable",
    "type": "constructor"
  },
  {
    "anonymous": false,
    "inputs": [
      {
        "indexed": true,
        "internalType": "address",
        "name": "owner",
        "type": "address"
      },
      {
        "indexed": true,
        "internalType": "address",
        "name": "spender",
        "type": "address"
      },
      {
        "indexed": false,
        "internalType": "uint256",
        "name": "value",
        "type": "uint256"
      }
    ],
    "name": "Approval",
    "type": "event"
  },
  {
    "anonymous": false,
    "inputs": [
      {
        "indexed": false,
        "internalType": "uint32",
        "name": "distributionID",
        "type": "uint32"
      },
      {
        "indexed": false,
        "internalType": "string",
        "name": "distributorName",
        "type": "string"
      },
      {
        "indexed": false,
        "internalType": "uint256",
        "name": "donationAmount",
        "type": "uint256"
      }
    ],
    "name": "LogDistributionRequest",
    "type": "event"
  },
  {
    "anonymous": false,
    "inputs": [
      {
        "indexed": false,
        "internalType": "uint32",
        "name": "distributionID",
        "type": "uint32"
      },
      {
        "indexed": false,
        "internalType": "string",
        "name": "distributorName",
        "type": "string"
      },
      {
        "indexed": false,
        "internalType": "string",
        "name": "donationName",
        "type": "string"
      },
      {
        "indexed": false,
        "internalType": "enum DonationManager.DistributionState",
        "name": "",
        "type": "uint8"
      }
    ],
    "name": "LogDistributionState",
    "type": "event"
  },
  {
    "anonymous": false,
    "inputs": [
      {
        "indexed": true,
        "internalType": "address",
        "name": "distributorAddress",
        "type": "address"
      },
      {
        "indexed": false,
        "internalType": "uint32",
        "name": "distributorID",
        "type": "uint32"
      },
      {
        "indexed": false,
        "internalType": "string",
        "name": "distributorName",
        "type": "string"
      },
      {
        "indexed": false,
        "internalType": "enum DonationManager.DistributorStatus",
        "name": "distributorStatus",
        "type": "uint8"
      }
    ],
    "name": "LogDistributorStatus",
    "type": "event"
  },
  {
    "anonymous": false,
    "inputs": [
      {
        "indexed": true,
        "internalType": "address",
        "name": "donorAddress",
        "type": "address"
      },
      {
        "indexed": false,
        "internalType": "uint256",
        "name": "withdrawAmount",
        "type": "uint256"
      },
      {
        "indexed": false,
        "internalType": "uint256",
        "name": "remainingBalance",
        "type": "uint256"
      }
    ],
    "name": "LogDistributorWithdrawal",
    "type": "event"
  },
  {
    "anonymous": false,
    "inputs": [
      {
        "indexed": false,
        "internalType": "uint32",
        "name": "donationID",
        "type": "uint32"
      },
      {
        "indexed": false,
        "internalType": "string",
        "name": "donationName",
        "type": "string"
      },
      {
        "indexed": false,
        "internalType": "enum DonationManager.DonationState",
        "name": "",
        "type": "uint8"
      }
    ],
    "name": "LogDonationState",
    "type": "event"
  },
  {
    "anonymous": false,
    "inputs": [
      {
        "indexed": true,
        "internalType": "address",
        "name": "donorAddress",
        "type": "address"
      },
      {
        "indexed": false,
        "internalType": "uint32",
        "name": "donorID",
        "type": "uint32"
      },
      {
        "indexed": false,
        "internalType": "uint256",
        "name": "balance",
        "type": "uint256"
      }
    ],
    "name": "LogDonorAdded",
    "type": "event"
  },
  {
    "anonymous": false,
    "inputs": [
      {
        "indexed": true,
        "internalType": "address",
        "name": "donorAddress",
        "type": "address"
      },
      {
        "indexed": false,
        "internalType": "uint256",
        "name": "donationAmount",
        "type": "uint256"
      }
    ],
    "name": "LogDonorDeposit",
    "type": "event"
  },
  {
    "anonymous": false,
    "inputs": [
      {
        "indexed": true,
        "internalType": "address",
        "name": "donorAddress",
        "type": "address"
      },
      {
        "indexed": false,
        "internalType": "uint256",
        "name": "withdrawAmount",
        "type": "uint256"
      },
      {
        "indexed": false,
        "internalType": "uint256",
        "name": "remainingBalance",
        "type": "uint256"
      }
    ],
    "name": "LogDonorWithdrawal",
    "type": "event"
  },
  {
    "anonymous": false,
    "inputs": [
      {
        "indexed": true,
        "internalType": "address",
        "name": "previousOwner",
        "type": "address"
      },
      {
        "indexed": true,
        "internalType": "address",
        "name": "newOwner",
        "type": "address"
      }
    ],
    "name": "OwnershipTransferred",
    "type": "event"
  },
  {
    "anonymous": false,
    "inputs": [
      {
        "indexed": false,
        "internalType": "address",
        "name": "account",
        "type": "address"
      }
    ],
    "name": "Paused",
    "type": "event"
  },
  {
    "anonymous": false,
    "inputs": [
      {
        "indexed": true,
        "internalType": "address",
        "name": "from",
        "type": "address"
      },
      {
        "indexed": true,
        "internalType": "address",
        "name": "to",
        "type": "address"
      },
      {
        "indexed": false,
        "internalType": "uint256",
        "name": "value",
        "type": "uint256"
      }
    ],
    "name": "Transfer",
    "type": "event"
  },
  {
    "anonymous": false,
    "inputs": [
      {
        "indexed": false,
        "internalType": "address",
        "name": "account",
        "type": "address"
      }
    ],
    "name": "Unpaused",
    "type": "event"
  },
  {
    "inputs": [
      {
        "internalType": "uint32",
        "name": "",
        "type": "uint32"
      }
    ],
    "name": "allDistributors",
    "outputs": [
      {
        "internalType": "uint32",
        "name": "distributorID",
        "type": "uint32"
      },
      {
        "internalType": "address",
        "name": "distributorAddress",
        "type": "address"
      },
      {
        "internalType": "string",
        "name": "distributorName",
        "type": "string"
      },
      {
        "internalType": "string",
        "name": "distributorCountry",
        "type": "string"
      },
      {
        "internalType": "enum DonationManager.DistributorStatus",
        "name": "distributorStatus",
        "type": "uint8"
      }
    ],
    "stateMutability": "view",
    "type": "function"
  },
  {
    "inputs": [
      {
        "internalType": "uint32",
        "name": "",
        "type": "uint32"
      }
    ],
    "name": "allDonors",
    "outputs": [
      {
        "internalType": "uint32",
        "name": "donorID",
        "type": "uint32"
      },
      {
        "internalType": "address",
        "name": "donorAddress",
        "type": "address"
      },
      {
        "internalType": "uint256",
        "name": "amountDonated",
        "type": "uint256"
      },
      {
        "internalType": "string",
        "name": "donorName",
        "type": "string"
      }
    ],
    "stateMutability": "view",
    "type": "function"
  },
  {
    "inputs": [
      {
        "internalType": "address",
        "name": "owner",
        "type": "address"
      },
      {
        "internalType": "address",
        "name": "spender",
        "type": "address"
      }
    ],
    "name": "allowance",
    "outputs": [
      {
        "internalType": "uint256",
        "name": "",
        "type": "uint256"
      }
    ],
    "stateMutability": "view",
    "type": "function"
  },
  {
    "inputs": [
      {
        "internalType": "address",
        "name": "spender",
        "type": "address"
      },
      {
        "internalType": "uint256",
        "name": "amount",
        "type": "uint256"
      }
    ],
    "name": "approve",
    "outputs": [
      {
        "internalType": "bool",
        "name": "",
        "type": "bool"
      }
    ],
    "stateMutability": "nonpayable",
    "type": "function"
  },
  {
    "inputs": [
      {
        "internalType": "address",
        "name": "account",
        "type": "address"
      }
    ],
    "name": "balanceOf",
    "outputs": [
      {
        "internalType": "uint256",
        "name": "",
        "type": "uint256"
      }
    ],
    "stateMutability": "view",
    "type": "function"
  },
  {
    "inputs": [],
    "name": "decimals",
    "outputs": [
      {
        "internalType": "uint8",
        "name": "",
        "type": "uint8"
      }
    ],
    "stateMutability": "view",
    "type": "function"
  },
  {
    "inputs": [
      {
        "internalType": "address",
        "name": "spender",
        "type": "address"
      },
      {
        "internalType": "uint256",
        "name": "subtractedValue",
        "type": "uint256"
      }
    ],
    "name": "decreaseAllowance",
    "outputs": [
      {
        "internalType": "bool",
        "name": "",
        "type": "bool"
      }
    ],
    "stateMutability": "nonpayable",
    "type": "function"
  },
  {
    "inputs": [],
    "name": "distributionCount",
    "outputs": [
      {
        "internalType": "uint32",
        "name": "",
        "type": "uint32"
      }
    ],
    "stateMutability": "view",
    "type": "function"
  },
  {
    "inputs": [
      {
        "internalType": "uint256",
        "name": "",
        "type": "uint256"
      }
    ],
    "name": "distributions",
    "outputs": [
      {
        "internalType": "uint32",
        "name": "distributionID",
        "type": "uint32"
      },
      {
        "internalType": "uint32",
        "name": "distributorID",
        "type": "uint32"
      },
      {
        "internalType": "uint32",
        "name": "donationID",
        "type": "uint32"
      },
      {
        "internalType": "uint32",
        "name": "donorID",
        "type": "uint32"
      },
      {
        "internalType": "uint256",
        "name": "distributionAmount",
        "type": "uint256"
      },
      {
        "internalType": "uint32",
        "name": "recipientCount",
        "type": "uint32"
      },
      {
        "internalType": "uint8",
        "name": "distributionMonths",
        "type": "uint8"
      },
      {
        "internalType": "bool",
        "name": "recipientDetailsAreValid",
        "type": "bool"
      },
      {
        "internalType": "enum DonationManager.DistributionState",
        "name": "distributionState",
        "type": "uint8"
      }
    ],
    "stateMutability": "view",
    "type": "function"
  },
  {
    "inputs": [],
    "name": "distributorCount",
    "outputs": [
      {
        "internalType": "uint32",
        "name": "",
        "type": "uint32"
      }
    ],
    "stateMutability": "view",
    "type": "function"
  },
  {
    "inputs": [],
    "name": "donationCount",
    "outputs": [
      {
        "internalType": "uint32",
        "name": "",
        "type": "uint32"
      }
    ],
    "stateMutability": "view",
    "type": "function"
  },
  {
    "inputs": [
      {
        "internalType": "uint256",
        "name": "",
        "type": "uint256"
      }
    ],
    "name": "donations",
    "outputs": [
      {
        "internalType": "uint32",
        "name": "donationID",
        "type": "uint32"
      },
      {
        "internalType": "uint32",
        "name": "donorID",
        "type": "uint32"
      },
      {
        "internalType": "string",
        "name": "donationName",
        "type": "string"
      },
      {
        "internalType": "uint256",
        "name": "donationAmount",
        "type": "uint256"
      },
      {
        "internalType": "uint256",
        "name": "donationGrantedAmount",
        "type": "uint256"
      },
      {
        "internalType": "uint256",
        "name": "requestedNotGrantedAmount",
        "type": "uint256"
      },
      {
        "internalType": "uint32",
        "name": "USDperRecipientPerMonth",
        "type": "uint32"
      },
      {
        "internalType": "uint8",
        "name": "adminFeePercent",
        "type": "uint8"
      },
      {
        "internalType": "enum DonationManager.DonationState",
        "name": "donationState",
        "type": "uint8"
      },
      {
        "internalType": "enum DonationManager.DonationPurpose",
        "name": "donationPurpose",
        "type": "uint8"
      }
    ],
    "stateMutability": "view",
    "type": "function"
  },
  {
    "inputs": [
      {
        "internalType": "address",
        "name": "",
        "type": "address"
      }
    ],
    "name": "donorBalances",
    "outputs": [
      {
        "internalType": "uint256",
        "name": "",
        "type": "uint256"
      }
    ],
    "stateMutability": "view",
    "type": "function"
  },
  {
    "inputs": [],
    "name": "donorCount",
    "outputs": [
      {
        "internalType": "uint32",
        "name": "",
        "type": "uint32"
      }
    ],
    "stateMutability": "view",
    "type": "function"
  },
  {
    "inputs": [
      {
        "internalType": "address",
        "name": "spender",
        "type": "address"
      },
      {
        "internalType": "uint256",
        "name": "addedValue",
        "type": "uint256"
      }
    ],
    "name": "increaseAllowance",
    "outputs": [
      {
        "internalType": "bool",
        "name": "",
        "type": "bool"
      }
    ],
    "stateMutability": "nonpayable",
    "type": "function"
  },
  {
    "inputs": [],
    "name": "name",
    "outputs": [
      {
        "internalType": "string",
        "name": "",
        "type": "string"
      }
    ],
    "stateMutability": "view",
    "type": "function"
  },
  {
    "inputs": [],
    "name": "owner",
    "outputs": [
      {
        "internalType": "address",
        "name": "",
        "type": "address"
      }
    ],
    "stateMutability": "view",
    "type": "function"
  },
  {
    "inputs": [],
    "name": "paused",
    "outputs": [
      {
        "internalType": "bool",
        "name": "",
        "type": "bool"
      }
    ],
    "stateMutability": "view",
    "type": "function"
  },
  {
    "inputs": [],
    "name": "renounceOwnership",
    "outputs": [],
    "stateMutability": "nonpayable",
    "type": "function"
  },
  {
    "inputs": [],
    "name": "symbol",
    "outputs": [
      {
        "internalType": "string",
        "name": "",
        "type": "string"
      }
    ],
    "stateMutability": "view",
    "type": "function"
  },
  {
    "inputs": [],
    "name": "totalSupply",
    "outputs": [
      {
        "internalType": "uint256",
        "name": "",
        "type": "uint256"
      }
    ],
    "stateMutability": "view",
    "type": "function"
  },
  {
    "inputs": [
      {
        "internalType": "address",
        "name": "recipient",
        "type": "address"
      },
      {
        "internalType": "uint256",
        "name": "amount",
        "type": "uint256"
      }
    ],
    "name": "transfer",
    "outputs": [
      {
        "internalType": "bool",
        "name": "",
        "type": "bool"
      }
    ],
    "stateMutability": "nonpayable",
    "type": "function"
  },
  {
    "inputs": [
      {
        "internalType": "address",
        "name": "sender",
        "type": "address"
      },
      {
        "internalType": "address",
        "name": "recipient",
        "type": "address"
      },
      {
        "internalType": "uint256",
        "name": "amount",
        "type": "uint256"
      }
    ],
    "name": "transferFrom",
    "outputs": [
      {
        "internalType": "bool",
        "name": "",
        "type": "bool"
      }
    ],
    "stateMutability": "nonpayable",
    "type": "function"
  },
  {
    "inputs": [
      {
        "internalType": "address",
        "name": "newOwner",
        "type": "address"
      }
    ],
    "name": "transferOwnership",
    "outputs": [],
    "stateMutability": "nonpayable",
    "type": "function"
  },
  {
    "inputs": [
      {
        "internalType": "string",
        "name": "_donorName",
        "type": "string"
      },
      {
        "internalType": "uint256",
        "name": "currentBalance",
        "type": "uint256"
      }
    ],
    "name": "createDonor",
    "outputs": [
      {
        "internalType": "bool",
        "name": "",
        "type": "bool"
      }
    ],
    "stateMutability": "payable",
    "type": "function"
  },
  {
    "inputs": [
      {
        "internalType": "string",
        "name": "_distributorName",
        "type": "string"
      },
      {
        "internalType": "string",
        "name": "_distributorCountry",
        "type": "string"
      }
    ],
    "name": "createDistributor",
    "outputs": [
      {
        "internalType": "bool",
        "name": "",
        "type": "bool"
      }
    ],
    "stateMutability": "nonpayable",
    "type": "function"
  },
  {
    "inputs": [
      {
        "internalType": "string",
        "name": "_donationName",
        "type": "string"
      },
      {
        "internalType": "uint32",
        "name": "_donorID",
        "type": "uint32"
      },
      {
        "internalType": "uint32",
        "name": "_USDperRecipientPerMonth",
        "type": "uint32"
      },
      {
        "internalType": "uint8",
        "name": "_adminFeePercent",
        "type": "uint8"
      }
    ],
    "name": "createDonation",
    "outputs": [
      {
        "internalType": "bool",
        "name": "",
        "type": "bool"
      }
    ],
    "stateMutability": "nonpayable",
    "type": "function"
  },
  {
    "inputs": [
      {
        "internalType": "uint256",
        "name": "_depositAmount",
        "type": "uint256"
      }
    ],
    "name": "donorDeposit",
    "outputs": [],
    "stateMutability": "payable",
    "type": "function"
  },
  {
    "inputs": [
      {
        "internalType": "uint256",
        "name": "_donationAmount",
        "type": "uint256"
      },
      {
        "internalType": "uint32",
        "name": "_donationID",
        "type": "uint32"
      }
    ],
    "name": "makeDonation",
    "outputs": [],
    "stateMutability": "nonpayable",
    "type": "function"
  },
  {
    "inputs": [
      {
        "internalType": "uint32",
        "name": "_distributorID",
        "type": "uint32"
      },
      {
        "internalType": "uint32",
        "name": "_distributorStatus",
        "type": "uint32"
      }
    ],
    "name": "changeDistributorStatus",
    "outputs": [],
    "stateMutability": "nonpayable",
    "type": "function"
  },
  {
    "inputs": [
      {
        "internalType": "uint32",
        "name": "_donationID",
        "type": "uint32"
      }
    ],
    "name": "getDonationBalance",
    "outputs": [
      {
        "internalType": "uint256",
        "name": "donatedAmount",
        "type": "uint256"
      },
      {
        "internalType": "uint256",
        "name": "grantedAmount",
        "type": "uint256"
      },
      {
        "internalType": "uint256",
        "name": "requestedNotGranted",
        "type": "uint256"
      }
    ],
    "stateMutability": "view",
    "type": "function"
  },
  {
    "inputs": [
      {
        "internalType": "uint32",
        "name": "_donorID",
        "type": "uint32"
      }
    ],
    "name": "getAllDonorBalances",
    "outputs": [
      {
        "internalType": "uint256",
        "name": "donatedAmount",
        "type": "uint256"
      },
      {
        "internalType": "uint256",
        "name": "grantedAmount",
        "type": "uint256"
      },
      {
        "internalType": "uint256",
        "name": "requestedNotGranted",
        "type": "uint256"
      },
      {
        "internalType": "uint256",
        "name": "fundsAvailableToWithdraw",
        "type": "uint256"
      }
    ],
    "stateMutability": "view",
    "type": "function"
  },
  {
    "inputs": [],
    "name": "getDistributorBalance",
    "outputs": [
      {
        "internalType": "uint256",
        "name": "availbleToWithdraw",
        "type": "uint256"
      }
    ],
    "stateMutability": "view",
    "type": "function"
  },
  {
    "inputs": [
      {
        "internalType": "uint32",
        "name": "_distributorID",
        "type": "uint32"
      },
      {
        "internalType": "uint32",
        "name": "_donationID",
        "type": "uint32"
      },
      {
        "internalType": "uint32",
        "name": "_recipientCount",
        "type": "uint32"
      },
      {
        "internalType": "uint8",
        "name": "_distributionMonths",
        "type": "uint8"
      },
      {
        "internalType": "bool",
        "name": "_recipientDetailsAreValid",
        "type": "bool"
      }
    ],
    "name": "createDistribution",
    "outputs": [
      {
        "internalType": "bool",
        "name": "",
        "type": "bool"
      }
    ],
    "stateMutability": "nonpayable",
    "type": "function"
  },
  {
    "inputs": [
      {
        "internalType": "uint32",
        "name": "_distributionID",
        "type": "uint32"
      }
    ],
    "name": "requestDonationFunds",
    "outputs": [],
    "stateMutability": "payable",
    "type": "function"
  },
  {
    "inputs": [
      {
        "internalType": "uint256",
        "name": "_withdrawAmount",
        "type": "uint256"
      },
      {
        "internalType": "uint32",
        "name": "_donorID",
        "type": "uint32"
      }
    ],
    "name": "donorWithdrawal",
    "outputs": [],
    "stateMutability": "payable",
    "type": "function"
  },
  {
    "inputs": [
      {
        "internalType": "uint256",
        "name": "_withdrawAmount",
        "type": "uint256"
      }
    ],
    "name": "distributorWithdrawal",
    "outputs": [],
    "stateMutability": "payable",
    "type": "function"
  },
  {
    "inputs": [],
    "name": "pause",
    "outputs": [],
    "stateMutability": "nonpayable",
    "type": "function"
  },
  {
    "inputs": [],
    "name": "unpause",
    "outputs": [],
    "stateMutability": "nonpayable",
    "type": "function"
  }
]